{
    "type": "FeatureCollection",
    "name": "FAS PENYEBERANGAN_temp",
    "crs": {
        "type": "name",
        "properties": {
            "name": "urn:ogc:def:crs:OGC:1.3:CRS84"
        }
    },
    "features": [
        {
            "type": "Feature",
            "properties": {
                "No": "1",
                "Detail Lokasi": null,
                "Dokumentasi": null,
                "Tahun Anggaran": null,
                "Jenis Penyeberangan": "Zebra Cross",
                "Kondisi": "Baik",
                "Keterangan Kondisi": null
            },
            "geometry": {
                "type": "Point",
                "coordinates": [
                    106.9164071,
                    -6.9478844
                ]
            }
        },
        {
            "type": "Feature",
            "properties": {
                "No": "2",
                "Detail Lokasi": null,
                "Dokumentasi": null,
                "Tahun Anggaran": null,
                "Jenis Penyeberangan": "Zebra Cross",
                "Kondisi": "Baik",
                "Keterangan Kondisi": null
            },
            "geometry": {
                "type": "Point",
                "coordinates": [
                    106.9328172,
                    -6.9504766
                ]
            }
        },
        {
            "type": "Feature",
            "properties": {
                "No": "3",
                "Detail Lokasi": null,
                "Dokumentasi": null,
                "Tahun Anggaran": null,
                "Jenis Penyeberangan": "Zebra Cross",
                "Kondisi": "Baik",
                "Keterangan Kondisi": null
            },
            "geometry": {
                "type": "Point",
                "coordinates": [
                    106.936413,
                    -6.9493445
                ]
            }
        },
        {
            "type": "Feature",
            "properties": {
                "No": "1",
                "Detail Lokasi": null,
                "Dokumentasi": null,
                "Tahun Anggaran": null,
                "Jenis Penyeberangan": "Zebra Cross",
                "Kondisi": "Baik",
                "Keterangan Kondisi": null
            },
            "geometry": {
                "type": "Point",
                "coordinates": [
                    106.9528399,
                    -6.9365965
                ]
            }
        },
        {
            "type": "Feature",
            "properties": {
                "No": "1",
                "Detail Lokasi": null,
                "Dokumentasi": null,
                "Tahun Anggaran": null,
                "Jenis Penyeberangan": "Zebra Cross",
                "Kondisi": "Baik",
                "Keterangan Kondisi": null
            },
            "geometry": {
                "type": "Point",
                "coordinates": [
                    106.9544198,
                    -6.9351941
                ]
            }
        },
        {
            "type": "Feature",
            "properties": {
                "No": "1",
                "Detail Lokasi": null,
                "Dokumentasi": null,
                "Tahun Anggaran": null,
                "Jenis Penyeberangan": "Zebra Cross",
                "Kondisi": "Baik",
                "Keterangan Kondisi": null
            },
            "geometry": {
                "type": "Point",
                "coordinates": [
                    106.955406,
                    -6.9343861
                ]
            }
        },
        {
            "type": "Feature",
            "properties": {
                "No": "1",
                "Detail Lokasi": null,
                "Dokumentasi": null,
                "Tahun Anggaran": null,
                "Jenis Penyeberangan": "Zebra Cross",
                "Kondisi": "Rusak Berat",
                "Keterangan Kondisi": "warna pudar"
            },
            "geometry": {
                "type": "Point",
                "coordinates": [
                    106.9593274,
                    -6.9305225
                ]
            }
        }
    ]
}