{
    "type": "FeatureCollection",
    "name": "RPPJ_temp",
    "crs": {
        "type": "name",
        "properties": {
            "name": "urn:ogc:def:crs:OGC:1.3:CRS84"
        }
    },
    "features": [
        {
            "type": "Feature",
            "properties": {
                "No": "1",
                "Detail Lokasi": "Depan Sebrang Klinik Praktek Doktor Umum",
                "Dokumentasi": null,
                "Gambar Rppj": null,
                "Tahun Anggaran": "Tidak Diketahui",
                "Lokasi Pemasangan Kiri": "1",
                "Lokasi Pemasangan Tengah": null,
                "Lokasi Pemasangan Kanan": null,
                "Kondisi": "Baik",
                "Keterangan Kondisi": null,
                "Jenis Tiang": "Tiang F"
            },
            "geometry": {
                "type": "Point",
                "coordinates": [
                    107.130925,
                    -6.5016547
                ]
            }
        }
    ]
}