{
    "type": "FeatureCollection",
    "name": "RAMBU_temp",
    "crs": {
        "type": "name",
        "properties": {
            "name": "urn:ogc:def:crs:OGC:1.3:CRS84"
        }
    },
    "features": [
        {
            "type": "Feature",
            "properties": {
                "No": "1",
                "Detail Lokasi": "Depan toko warnet dan fotocopy",
                "Dokumentasi": null,
                "Nomor Tabel": "1f",
                "Gambar Rambu": null,
                "Nama Rambu": null,
                "Jenis Rambu Larangan": null,
                "Jenis Rambu Peringatan": null,
                "Jenis Rambu Perintah": null,
                "Jenis Rambu Petunjuk": "1",
                "Tahun Anggaran": "Tidak Diketahui",
                "Lokasi Pemasangan Kiri": null,
                "Lokasi Pemasangan Tengah": null,
                "Lokasi Pemasangan Kanan": "1",
                "Kondisi": "Baik",
                "Keterangan Kondisi": null,
                "Tipe Rambu": "Tiang Tunggal"
            },
            "geometry": {
                "type": "Point",
                "coordinates": [
                    107.2174975,
                    -6.5091154
                ]
            }
        },
        {
            "type": "Feature",
            "properties": {
                "No": "2",
                "Detail Lokasi": "Ciaru",
                "Dokumentasi": null,
                "Nomor Tabel": "1e",
                "Gambar Rambu": null,
                "Nama Rambu": null,
                "Jenis Rambu Larangan": null,
                "Jenis Rambu Peringatan": null,
                "Jenis Rambu Perintah": null,
                "Jenis Rambu Petunjuk": "1",
                "Tahun Anggaran": "Tidak Diketahui",
                "Lokasi Pemasangan Kiri": null,
                "Lokasi Pemasangan Tengah": null,
                "Lokasi Pemasangan Kanan": "1",
                "Kondisi": "Baik",
                "Keterangan Kondisi": null,
                "Tipe Rambu": "Tiang Tunggal"
            },
            "geometry": {
                "type": "Point",
                "coordinates": [
                    107.2161641,
                    -6.5093795
                ]
            }
        }
    ]
}