{
    "type": "FeatureCollection",
    "name": "RPPJ_temp",
    "crs": {
        "type": "name",
        "properties": {
            "name": "urn:ogc:def:crs:OGC:1.3:CRS84"
        }
    },
    "features": [
        {
            "type": "Feature",
            "properties": {
                "No": "1",
                "Detail Lokasi": null,
                "Dokumentasi": null,
                "Gambar Rppj": null,
                "Tahun Anggaran": "Tidak Diketahui",
                "Lokasi Pemasangan Kiri": "1",
                "Lokasi Pemasangan Tengah": null,
                "Lokasi Pemasangan Kanan": null,
                "Kondisi": "Rusak Berat",
                "Keterangan Kondisi": null,
                "Jenis Tiang": "Tiang Tunggal"
            },
            "geometry": {
                "type": "Point",
                "coordinates": [
                    107.17888,
                    -6.270785
                ]
            }
        },
        {
            "type": "Feature",
            "properties": {
                "No": "2",
                "Detail Lokasi": null,
                "Dokumentasi": null,
                "Gambar Rppj": null,
                "Tahun Anggaran": "Tidak Diketahui",
                "Lokasi Pemasangan Kiri": "1",
                "Lokasi Pemasangan Tengah": null,
                "Lokasi Pemasangan Kanan": null,
                "Kondisi": "Baik",
                "Keterangan Kondisi": null,
                "Jenis Tiang": "Tiang F"
            },
            "geometry": {
                "type": "Point",
                "coordinates": [
                    107.175913,
                    -6.272253
                ]
            }
        },
        {
            "type": "Feature",
            "properties": {
                "No": "3",
                "Detail Lokasi": null,
                "Dokumentasi": null,
                "Gambar Rppj": null,
                "Tahun Anggaran": "Tidak Diketahui",
                "Lokasi Pemasangan Kiri": "1",
                "Lokasi Pemasangan Tengah": null,
                "Lokasi Pemasangan Kanan": null,
                "Kondisi": "Baik",
                "Keterangan Kondisi": null,
                "Jenis Tiang": "Tiang F"
            },
            "geometry": {
                "type": "Point",
                "coordinates": [
                    107.168088,
                    -6.278583
                ]
            }
        },
        {
            "type": "Feature",
            "properties": {
                "No": "4",
                "Detail Lokasi": null,
                "Dokumentasi": null,
                "Gambar Rppj": null,
                "Tahun Anggaran": "Tidak Diketahui",
                "Lokasi Pemasangan Kiri": "1",
                "Lokasi Pemasangan Tengah": null,
                "Lokasi Pemasangan Kanan": null,
                "Kondisi": "Baik",
                "Keterangan Kondisi": null,
                "Jenis Tiang": "Tiang F"
            },
            "geometry": {
                "type": "Point",
                "coordinates": [
                    107.167825,
                    -6.278784
                ]
            }
        },
        {
            "type": "Feature",
            "properties": {
                "No": "5",
                "Detail Lokasi": null,
                "Dokumentasi": null,
                "Gambar Rppj": null,
                "Tahun Anggaran": "Tidak Diketahui",
                "Lokasi Pemasangan Kiri": "1",
                "Lokasi Pemasangan Tengah": null,
                "Lokasi Pemasangan Kanan": null,
                "Kondisi": "Rusak Berat",
                "Keterangan Kondisi": null,
                "Jenis Tiang": "Tiang F"
            },
            "geometry": {
                "type": "Point",
                "coordinates": [
                    107.165665,
                    -6.280411
                ]
            }
        },
        {
            "type": "Feature",
            "properties": {
                "No": "6",
                "Detail Lokasi": null,
                "Dokumentasi": null,
                "Gambar Rppj": null,
                "Tahun Anggaran": "Tidak Diketahui",
                "Lokasi Pemasangan Kiri": "1",
                "Lokasi Pemasangan Tengah": null,
                "Lokasi Pemasangan Kanan": null,
                "Kondisi": "Baik",
                "Keterangan Kondisi": null,
                "Jenis Tiang": "Tiang F"
            },
            "geometry": {
                "type": "Point",
                "coordinates": [
                    107.15414,
                    -6.288372
                ]
            }
        }
    ]
}