{
    "type": "FeatureCollection",
    "name": "MARKA_temp",
    "crs": {
        "type": "name",
        "properties": {
            "name": "urn:ogc:def:crs:OGC:1.3:CRS84"
        }
    },
    "features": [
        {
            "type": "Feature",
            "properties": {
                "No": "1",
                "Detail Lokasi": "Turunan jl. Geopark Palabuhanratu",
                "Dokumentasi": null,
                "Tahun Anggaran": "Tidak Diketahui",
                "Jenis Marka": "Marka Tengah",
                "Kondisi": "Baik",
                "Keterangan Kondisi": null,
                "Panjang Marka (m)": "2,3 KM"
            },
            "geometry": {
                "type": "Point",
                "coordinates": [
                    106.5598611,
                    -7.040162
                ]
            }
        },
        {
            "type": "Feature",
            "properties": {
                "No": "2",
                "Detail Lokasi": "Depan tempat pemakaman umum",
                "Dokumentasi": null,
                "Tahun Anggaran": "Tidak Diketahui",
                "Jenis Marka": "Marka Tengah",
                "Kondisi": "Baik",
                "Keterangan Kondisi": null,
                "Panjang Marka (m)": "12,3 KM"
            },
            "geometry": {
                "type": "Point",
                "coordinates": [
                    106.5476257,
                    -7.0513141
                ]
            }
        },
        {
            "type": "Feature",
            "properties": {
                "No": "3",
                "Detail Lokasi": null,
                "Dokumentasi": null,
                "Tahun Anggaran": "Tidak Diketahui",
                "Jenis Marka": "Marka Tengah",
                "Kondisi": "Baik",
                "Keterangan Kondisi": null,
                "Panjang Marka (m)": "2,5 KM"
            },
            "geometry": {
                "type": "Point",
                "coordinates": [
                    106.559529,
                    -7.040064
                ]
            }
        },
        {
            "type": "Feature",
            "properties": {
                "No": "4",
                "Detail Lokasi": null,
                "Dokumentasi": null,
                "Tahun Anggaran": "Tidak Diketahui",
                "Jenis Marka": "Marka Tengah",
                "Kondisi": "Baik",
                "Keterangan Kondisi": null,
                "Panjang Marka (m)": "3 KM"
            },
            "geometry": {
                "type": "Point",
                "coordinates": [
                    106.475792,
                    -7.167074
                ]
            }
        }
    ]
}