{
    "type": "FeatureCollection",
    "name": "MARKA (baru)_temp",
    "crs": {
        "type": "name",
        "properties": {
            "name": "urn:ogc:def:crs:OGC:1.3:CRS84"
        }
    },
    "features": [
        {
            "type": "Feature",
            "properties": {
                "No": "1",
                "Detail Lokasi": null,
                "Dokumentasi": "#VALUE!",
                "Tahun Anggaran": null,
                "Jenis Marka": "PITA KEJUT",
                "Kondisi": "Pudar",
                "Keterangan Kondisi": "Memudar",
                "Panjang Marka (m)": "30"
            },
            "geometry": {
                "type": "Point",
                "coordinates": [
                    107.0098711,
                    -6.247025
                ]
            }
        },
        {
            "type": "Feature",
            "properties": {
                "No": "2",
                "Detail Lokasi": null,
                "Dokumentasi": "#VALUE!",
                "Tahun Anggaran": null,
                "Jenis Marka": "PITA KEJUT",
                "Kondisi": "Pudar",
                "Keterangan Kondisi": "Memudar",
                "Panjang Marka (m)": "30"
            },
            "geometry": {
                "type": "Point",
                "coordinates": [
                    107.0081666,
                    -6.2456546
                ]
            }
        }
    ]
}